my_tensor/__init__.py
my_tensor/tensor.py
my_tensor-0.1.0.dist-info/METADATA
my_tensor-0.1.0.dist-info/WHEEL
my_tensor-0.1.0.dist-info/RECORD
